serpost/__init__.py
serpost/aio.py
serpost/cmd.py
serpost/formatters.py
serpost/payload.py
serpost/processors.py
serpost/url.py
py_serpost-0.4.2.dist-info/LICENSE.txt
py_serpost-0.4.2.dist-info/METADATA
py_serpost-0.4.2.dist-info/WHEEL
py_serpost-0.4.2.dist-info/entry_points.txt
py_serpost-0.4.2.dist-info/top_level.txt
py_serpost-0.4.2.dist-info/RECORD
