Metadata-Version: 2.1
Name: py-serpost
Version: 0.4.2
Summary: Tracking de paquetes de Serpost Perú sin autenticación
Home-page: https://github.com/wesitos/py-serpost
Author: Pedro Palacios
License: GPL-3.0+
Keywords: serpost tracking
Platform: UNKNOWN
Classifier: Development Status :: 4 - Beta
Classifier: Environment :: Console
Classifier: Framework :: AsyncIO
Classifier: Intended Audience :: End Users/Desktop
Classifier: Intended Audience :: Developers
Classifier: License :: OSI Approved :: GNU General Public License v3 or later (GPLv3+)
Classifier: Operating System :: OS Independent
Classifier: Programming Language :: Python :: 3
Classifier: Programming Language :: Python :: 3.5
Classifier: Programming Language :: Python :: 3.6
Classifier: Topic :: Utilities
Requires-Python: >=3.5.3
Requires-Dist: aiohttp (>=3.1.3)
Requires-Dist: pyyaml (>=5)
